CHANGES.rst
CONTRIBUTORS.txt
LICENSE.txt
MANIFEST.in
README.rst
setup.py
mediamosa/__init__.py
mediamosa/api.py
mediamosa/errors.py
mediamosa/resources.py
mediamosa/response.py
mediamosa.egg-info/PKG-INFO
mediamosa.egg-info/SOURCES.txt
mediamosa.egg-info/dependency_links.txt
mediamosa.egg-info/requires.txt
mediamosa.egg-info/top_level.txt
tests/__init__.py
tests/test_api_login.py
tests/test_asset_resource.py
tests/test_assetlist_resource.py
tests/test_mediafile_resource.py
tests/test_mediamosa_resource.py