Metadata-Version: 1.1
Name: mediamosa
Version: 0.0.5
Summary: A high-level API interface for MediaMosa.
Home-page: https://github.com/UGentPortaal/python-mediamosa
Author: UGent Portaal Team
Author-email: portaal-tech@ugent.be
License: BSD
Platform: UNKNOWN
Classifier: Development Status :: 3 - Alpha
Classifier: Environment :: Console
Classifier: Environment :: Web Environment
Classifier: Intended Audience :: End Users/Desktop
Classifier: Intended Audience :: Developers
Classifier: Intended Audience :: System Administrators
Classifier: License :: OSI Approved :: BSD License
Classifier: Operating System :: MacOS :: MacOS X
Classifier: Operating System :: Microsoft :: Windows
Classifier: Operating System :: POSIX
Classifier: Programming Language :: Python
Classifier: Topic :: Internet :: WWW/HTTP :: Dynamic Content
Classifier: Topic :: Multimedia :: Video
Classifier: Topic :: Software Development :: Libraries
Classifier: Topic :: Utilities
